fgpyo/__init__.py
fgpyo/py.typed
fgpyo/read_structure.py
fgpyo/sequence.py
fgpyo/collections/__init__.py
fgpyo/fasta/__init__.py
fgpyo/fasta/builder.py
fgpyo/fasta/sequence_dictionary.py
fgpyo/fastx/__init__.py
fgpyo/io/__init__.py
fgpyo/platform/__init__.py
fgpyo/platform/illumina.py
fgpyo/sam/__init__.py
fgpyo/sam/builder.py
fgpyo/sam/clipping.py
fgpyo/util/__init__.py
fgpyo/util/inspect.py
fgpyo/util/logging.py
fgpyo/util/metric.py
fgpyo/util/string.py
fgpyo/util/types.py
fgpyo/vcf/__init__.py
fgpyo/vcf/builder.py
fgpyo-1.3.0.dist-info/METADATA
fgpyo-1.3.0.dist-info/WHEEL
fgpyo-1.3.0.dist-info/licenses/LICENSE
fgpyo-1.3.0.dist-info/RECORD
