Metadata-Version: 2.4
Name: fgpyo
Version: 1.3.0
Summary: Python bioinformatics and genomics library
Project-URL: Homepage, https://github.com/fulcrumgenomics/fgpyo
Project-URL: Repository, https://github.com/fulcrumgenomics/fgpyo
Author: Nils Homer, Tim Fennell, Nathan Roach
License-Expression: MIT
License-File: LICENSE
Keywords: bioinformatics
Classifier: Development Status :: 5 - Production/Stable
Classifier: Environment :: Console
Classifier: Intended Audience :: Developers
Classifier: Intended Audience :: Science/Research
Classifier: License :: OSI Approved :: MIT License
Classifier: Natural Language :: English
Classifier: Operating System :: OS Independent
Classifier: Programming Language :: Python :: 3
Classifier: Programming Language :: Python :: 3.9
Classifier: Programming Language :: Python :: 3.10
Classifier: Programming Language :: Python :: 3.11
Classifier: Programming Language :: Python :: 3.12
Classifier: Programming Language :: Python :: 3.13
Classifier: Topic :: Scientific/Engineering :: Bio-Informatics
Classifier: Topic :: Software Development :: Documentation
Classifier: Topic :: Software Development :: Libraries :: Python Modules
Classifier: Typing :: Typed
Requires-Python: <4.0,>=3.9.0
Requires-Dist: attrs>=19.3.0
Requires-Dist: pysam>=0.22.1
Requires-Dist: strenum<0.5,>=0.4.15
Requires-Dist: typing-extensions>=4.12.2; python_version < '3.13'
Requires-Dist: zlib-ng>=0.5.1
